setup.py
chainer_libdnn.egg-info/PKG-INFO
chainer_libdnn.egg-info/SOURCES.txt
chainer_libdnn.egg-info/dependency_links.txt
chainer_libdnn.egg-info/pbr.json
chainer_libdnn.egg-info/top_level.txt
libdnn/__init__.py
libdnn/autoencoder.py
libdnn/classification.py
libdnn/nnbase.py
libdnn/regression.py
libdnn/visualizer.py