Metadata-Version: 1.0
Name: chainer-libdnn
Version: 2.0.2
Summary: General utilities for neural networs with chainer
Home-page: http://git.tochikuji.com/tochikuji/chainer-libcnn
Author: Aiga SUZUKI
Author-email: ai-suzuki@aist.go.jp
License: MIT
Platform: UNKNOWN
